AUTHORS
LICENSE
MANIFEST.in
README
README.md
setup.cfg
setup.py
demo/demo.py
gearbox/__init__.py
gearbox/doc/__init__.py
gearbox/doc/source/__init__.py
gearbox/doc/source/conf.py
gearbox/doc/source/index.rst
gearbox/export/__init__.py
gearbox/export/export.py
gearbox/export/templates/abaqus_gear.template
gearbox/export/templates/abaqus_gear3D.template
gearbox/export/templates/abaqus_pair.template
gearbox/export/templates/abaqus_pair3D.template
gearbox/export/templates/ansys_gear.template
gearbox/export/templates/comsol_gear.template
gearbox/export/templates/comsol_gear3D.template
gearbox/export/templates/comsol_pair.template
gearbox/export/templates/comsol_pair3D.template
gearbox/libs/__init__.py
gearbox/libs/gearprofile.py
gearbox/libs/maths.py
gearbox/standards/__init__.py
gearbox/standards/agma.py
gearbox/standards/iso.py
gearbox/transmition/__init__.py
gearbox/transmition/gears.py
python_gearbox.egg-info/PKG-INFO
python_gearbox.egg-info/SOURCES.txt
python_gearbox.egg-info/dependency_links.txt
python_gearbox.egg-info/not-zip-safe
python_gearbox.egg-info/pbr.json
python_gearbox.egg-info/requires.txt
python_gearbox.egg-info/top_level.txt