Metadata-Version: 1.1
Name: python-gearbox
Version: 0.1.2.dev
Summary: Python library for gear transmission design
Home-page: https://github.com/efirvida/python-gearbox
Author: Eduardo M. Firvida Donestevez
Author-email: efirvida@gmail.com
License: MIT
Download-URL: https://github.com/efirvida/python-gearbox/archive/master.zip
Keywords: gearbox,gear,agma,iso,gear transmission,engineering
Platform: any
Classifier: Intended Audience :: Developers
Classifier: Intended Audience :: Manufacturing
Classifier: Intended Audience :: Science/Research
Classifier: Natural Language :: English
Classifier: Programming Language :: Python
Classifier: Programming Language :: Python :: 2.7
Classifier: Topic :: Scientific/Engineering
Classifier: Topic :: Scientific/Engineering :: Human Machine Interfaces
Classifier: Topic :: Software Development
Classifier: Topic :: Software Development :: Libraries
